django_svelte_jsoneditor/__init__.py
django_svelte_jsoneditor/apps.py
django_svelte_jsoneditor/exceptions.py
django_svelte_jsoneditor/settings.py
django_svelte_jsoneditor/static/django_svelte_jsoneditor/.gitignore
django_svelte_jsoneditor/static/django_svelte_jsoneditor/css/svelte_jsoneditor.css
django_svelte_jsoneditor/static/django_svelte_jsoneditor/js/svelte_jsoneditor.js
django_svelte_jsoneditor/templates/django_svelte_jsoneditor/.gitignore
django_svelte_jsoneditor/templates/django_svelte_jsoneditor/widgets/svelte_jsoneditor.html
django_svelte_jsoneditor/widgets.py
django_svelte_jsoneditor-0.4.4.dist-info/LICENSE
django_svelte_jsoneditor-0.4.4.dist-info/METADATA
django_svelte_jsoneditor-0.4.4.dist-info/WHEEL
django_svelte_jsoneditor-0.4.4.dist-info/RECORD
