Metadata-Version: 2.3
Name: django-svelte-jsoneditor
Version: 0.4.4
Summary: A widget for django's JSONField using the latest-and-greatest Json Editor
License: MIT
Keywords: django,json,editor,svelte,jsoneditor,field,widget
Author: Tom Clark
Author-email: tom@octue.com
Requires-Python: >=3.9,<4.0
Classifier: Development Status :: 5 - Production/Stable
Classifier: Framework :: Django
Classifier: Intended Audience :: Developers
Classifier: License :: OSI Approved :: MIT License
Classifier: Operating System :: OS Independent
Classifier: Programming Language :: Python :: 3
Classifier: Programming Language :: Python :: 3.9
Classifier: Programming Language :: Python :: 3.10
Classifier: Programming Language :: Python :: 3.11
Classifier: Programming Language :: Python :: 3.12
Classifier: Programming Language :: Python :: 3.13
Classifier: Topic :: Software Development :: Libraries :: Python Modules
Requires-Dist: django (>=3.1) ; python_version >= "3.10" and python_version < "4.0"
Requires-Dist: django (>=4.0,<5.0) ; python_version == "3.9"
Project-URL: Repository, https://github.com/octue/django-svelte-jsoneditor
